setup.py
calculador_de_viga/calculador_de_viga.py
calculador_de_viga.egg-info/PKG-INFO
calculador_de_viga.egg-info/SOURCES.txt
calculador_de_viga.egg-info/dependency_links.txt
calculador_de_viga.egg-info/requires.txt
calculador_de_viga.egg-info/top_level.txt