Metadata-Version: 1.0
Name: calculador-de-viga
Version: 0.0.10
Summary: Calculador de Elementos Estruturais
Home-page: https://github.com/doglinhaskkk/calculador_de_vigas
Author: Doglas Rocha
Author-email: doglasfmr@gmail.com
License: Boost Software License
Keywords: Vigas,Pilares
Platform: UNKNOWN
